{
  "project_info": {
    "project_number": "345230342302",
    "project_id": "rn-social-app-f7fd1",
    "storage_bucket": "rn-social-app-f7fd1.appspot.com"
  },
  "client": [
    {
      "client_info": {
        "mobilesdk_app_id": "1:345230342302:android:118cf065917a2eac90a38f",
        "android_client_info": {
          "package_name": "com.firebase"
        }
      },
      "oauth_client": [
        {
          "client_id": "345230342302-ifn5sf3b1agh6puuej419oobh859tbr4.apps.googleusercontent.com",
          "client_type": 3
        }
      ],
      "api_key": [
        {
          "current_key": "AIzaSyCWdH_59fW7rih2XyM0smbsPA4sPHP2Vsw"
        }
      ],
      "services": {
        "appinvite_service": {
          "other_platform_oauth_client": [
            {
              "client_id": "345230342302-ifn5sf3b1agh6puuej419oobh859tbr4.apps.googleusercontent.com",
              "client_type": 3
            }
          ]
        }
      }
    }
  ],
  "configuration_version": "1"
}